wabbit_wappa/active_interactor.py
wabbit_wappa/active_learner.py
wabbit_wappa/__init__.py
wabbit_wappa-0.2.0.dist-info/DESCRIPTION.rst
wabbit_wappa-0.2.0.dist-info/METADATA
wabbit_wappa-0.2.0.dist-info/metadata.json
wabbit_wappa-0.2.0.dist-info/RECORD
wabbit_wappa-0.2.0.dist-info/top_level.txt
wabbit_wappa-0.2.0.dist-info/WHEEL
