Metadata-Version: 2.0
Name: wabbit-wappa
Version: 0.2.0
Summary: Wabbit Wappa is a full-featured Python wrapper for the Vowpal Wabbit machine learning utility.
Home-page: https://github.com/mokelly/wabbit_wappa
Author: Michael J.T. O'Kelly
Author-email: mokelly@gmail.com
License: MIT
Keywords: wabbit_wappa
Platform: UNKNOWN
Classifier: Development Status :: 4 - Beta
Classifier: Intended Audience :: Developers
Classifier: License :: OSI Approved :: MIT License
Classifier: Natural Language :: English
Classifier: Operating System :: Unix
Classifier: Programming Language :: Python :: 2
Classifier: Programming Language :: Python :: 2.6
Classifier: Programming Language :: Python :: 2.7
Requires-Dist: pexpect
Requires-Dist: pytest
Requires-Dist: cookiecutter
Requires-Dist: wheel (>=0.22)
Requires-Dist: pip (>=1.4)
